{
    "name": "Dictionary",
    "fields": [
        {
            "fieldName": "code",
            "fieldType": "String"
        },
        {
            "fieldName": "label",
            "fieldType": "String"
        },
        {
            "fieldName": "descr",
            "fieldType": "String"
        },
        {
            "fieldName": "category",
            "fieldType": "String"
        }
    ],
    "relationships": [],
    "changelogDate": "20200503170918",
    "entityTableName": "dictionary",
    "dto": "no",
    "pagination": "no",
    "service": "serviceClass",
    "jpaMetamodelFiltering": true,
    "fluentMethods": true,
    "readOnly": false,
    "clientRootFolder": "",
    "applications": "*"
}